tmplcl/__init__.py
tmplcl/app.py
tmplcl/commands.py
tmplcl/models.py
tmplcl/utils.py
tmplcl-0.1.1.dist-info/WHEEL
tmplcl-0.1.1.dist-info/entry_points.txt
tmplcl-0.1.1.dist-info/METADATA
tmplcl-0.1.1.dist-info/RECORD
