Metadata-Version: 2.3
Name: tmplcl
Version: 0.1.1
Summary: A utility for quickly copying a given string (template) to your clipboard
Keywords: CLI tools,copy-to-clipboard
Author: delfanbaum
Author-email: delfanbaum <delfanbaum@oreilly.com>
Requires-Dist: pydantic>=2.11.7
Requires-Dist: pyperclip>=1.9.0
Requires-Dist: tinydb>=4.8.2
Requires-Dist: typer>=0.16.1
Requires-Dist: xdg-base-dirs>=6.0.2
Requires-Python: >=3.13
